django_hook/__init__.py
django_hook/core.py
django_hook/decorators.py
django_hook/registry.py
django_hook/utils.py
django_hook-1.0.0.dist-info/licenses/LICENSE
django_hook-1.0.0.dist-info/METADATA
django_hook-1.0.0.dist-info/WHEEL
django_hook-1.0.0.dist-info/top_level.txt
django_hook-1.0.0.dist-info/RECORD
