Metadata-Version: 2.4
Name: django-hook
Version: 1.0.0
Summary: A powerful and flexible hook system for Django applications
Author-email: Amir Koulivand <vispa.amir@gmail.com>
Maintainer-email: Amir Koulivand <vispa.amir@gmail.com>
License: MIT
Project-URL: Homepage, https://github.com/vispamir/django-hook
Project-URL: Documentation, https://github.com/vispamir/django-hook#readme
Project-URL: Repository, https://github.com/vispamir/django-hook
Project-URL: Changelog, https://github.com/vispamir/django-hook/releases
Project-URL: Issues, https://github.com/vispamir/django-hook/issues
Keywords: django,hooks,plugins,extensibility,events,signals
Classifier: Development Status :: 5 - Production/Stable
Classifier: Environment :: Web Environment
Classifier: Framework :: Django
Classifier: Framework :: Django :: 5.2
Classifier: Intended Audience :: Developers
Classifier: License :: OSI Approved :: MIT License
Classifier: Operating System :: OS Independent
Classifier: Programming Language :: Python
Classifier: Programming Language :: Python :: 3
Classifier: Programming Language :: Python :: 3.12
Classifier: Topic :: Software Development :: Libraries :: Application Frameworks
Requires-Python: >=3.12
License-File: LICENSE
Requires-Dist: Django>=5.2
Provides-Extra: dev
Requires-Dist: pytest>=7.0.0; extra == "dev"
Requires-Dist: pytest-django>=4.5.0; extra == "dev"
Requires-Dist: black>=22.0.0; extra == "dev"
Requires-Dist: flake8>=5.0.0; extra == "dev"
Requires-Dist: isort>=5.10.0; extra == "dev"
Requires-Dist: mypy>=0.990; extra == "dev"
Requires-Dist: tox>=4.0.0; extra == "dev"
Requires-Dist: coverage>=6.0.0; extra == "dev"
Requires-Dist: sphinx>=5.0.0; extra == "dev"
Requires-Dist: sphinx-rtd-theme>=1.0.0; extra == "dev"
Provides-Extra: docs
Requires-Dist: sphinx>=5.0.0; extra == "docs"
Requires-Dist: sphinx-rtd-theme>=1.0.0; extra == "docs"
Requires-Dist: sphinx-autodoc-typehints>=1.19.0; extra == "docs"
Dynamic: license-file
